perform_topsis/102103759.py
Topsis_Suvansh_Gupta_102103759-1.0.0.dist-info/LICENSE
Topsis_Suvansh_Gupta_102103759-1.0.0.dist-info/METADATA
Topsis_Suvansh_Gupta_102103759-1.0.0.dist-info/WHEEL
Topsis_Suvansh_Gupta_102103759-1.0.0.dist-info/entry_points.txt
Topsis_Suvansh_Gupta_102103759-1.0.0.dist-info/top_level.txt
Topsis_Suvansh_Gupta_102103759-1.0.0.dist-info/RECORD
