Metadata-Version: 2.1
Name: Topsis-Suvansh_Gupta-102103759
Version: 1.0.0
Summary: Performs TOPSIS
Home-page: https://github.com/Suvansh03/Topsis-Implementation.git
Author: Suvansh Gupta
Author-email: sgupta22_be21@thapar.edu
License: MIT
Classifier: License :: OSI Approved :: MIT License
Classifier: Programming Language :: Python :: 3.6
Classifier: Programming Language :: Python :: 3.7
Classifier: Programming Language :: Python :: 3.8
License-File: LICENSE
